hjeon139_mcp_outofcontext/__init__.py
hjeon139_mcp_outofcontext/app_state.py
hjeon139_mcp_outofcontext/config.py
hjeon139_mcp_outofcontext/fastmcp_server.py
hjeon139_mcp_outofcontext/main.py
hjeon139_mcp_outofcontext/prompts.py
hjeon139_mcp_outofcontext/storage/__init__.py
hjeon139_mcp_outofcontext/storage/mdc_storage.py
hjeon139_mcp_outofcontext/tools/__init__.py
hjeon139_mcp_outofcontext/tools/crud/__init__.py
hjeon139_mcp_outofcontext/tools/crud/delete_context.py
hjeon139_mcp_outofcontext/tools/crud/get_context.py
hjeon139_mcp_outofcontext/tools/crud/models.py
hjeon139_mcp_outofcontext/tools/crud/put_context.py
hjeon139_mcp_outofcontext/tools/query/__init__.py
hjeon139_mcp_outofcontext/tools/query/list_context.py
hjeon139_mcp_outofcontext/tools/query/models.py
hjeon139_mcp_outofcontext/tools/query/search_context.py
hjeon139_mcp_outofcontext-1.0.1.dist-info/METADATA
hjeon139_mcp_outofcontext-1.0.1.dist-info/WHEEL
hjeon139_mcp_outofcontext-1.0.1.dist-info/entry_points.txt
hjeon139_mcp_outofcontext-1.0.1.dist-info/licenses/LICENSE
hjeon139_mcp_outofcontext-1.0.1.dist-info/RECORD
