Metadata-Version: 2.4
Name: hjeon139-mcp-outofcontext
Version: 1.0.1
Summary: MCP server for context management with markdown storage, CRUD operations, and search
Project-URL: Homepage, https://github.com/HJeon139/hjeon139-mcp-outofcontext
Project-URL: Repository, https://github.com/HJeon139/hjeon139-mcp-outofcontext
Project-URL: Issues, https://github.com/HJeon139/hjeon139-mcp-outofcontext/issues
Project-URL: Changelog, https://github.com/HJeon139/hjeon139-mcp-outofcontext/releases
Author-email: Hal Jeon <hjeon139@gmail.com>
License: Apache-2.0
License-File: LICENSE
Keywords: ai,context-management,fastmcp,llm,mcp,memory,model-context-protocol
Classifier: Development Status :: 5 - Production/Stable
Classifier: Intended Audience :: Developers
Classifier: License :: OSI Approved :: Apache Software License
Classifier: Programming Language :: Python :: 3
Classifier: Programming Language :: Python :: 3.11
Classifier: Programming Language :: Python :: 3.12
Classifier: Topic :: Scientific/Engineering :: Artificial Intelligence
Classifier: Topic :: Software Development :: Libraries :: Python Modules
Requires-Python: >=3.11
Requires-Dist: fastmcp>=2.11.0
Requires-Dist: pydantic>=2.0.0
Requires-Dist: pyyaml>=6.0.0
Provides-Extra: dev
Requires-Dist: mypy>=1.11.0; extra == 'dev'
Requires-Dist: pre-commit>=3.6.0; extra == 'dev'
Requires-Dist: pytest-asyncio>=0.23.0; extra == 'dev'
Requires-Dist: pytest-cov>=5.0.0; extra == 'dev'
Requires-Dist: pytest>=8.0.0; extra == 'dev'
Requires-Dist: ruff>=0.6.0; extra == 'dev'
Requires-Dist: types-pyyaml>=6.0.0; extra == 'dev'
